iotest/__init__.py
iotest/harness.py
iotest_grader-0.0.10.dist-info/LICENSE
iotest_grader-0.0.10.dist-info/METADATA
iotest_grader-0.0.10.dist-info/WHEEL
iotest_grader-0.0.10.dist-info/top_level.txt
iotest_grader-0.0.10.dist-info/RECORD
